twisted/__init__.py
twisted/__main__.py
twisted/_version.py
twisted/copyright.py
twisted/plugin.py
twisted/_threads/__init__.py
twisted/_threads/_convenience.py
twisted/_threads/_ithreads.py
twisted/_threads/_memory.py
twisted/_threads/_pool.py
twisted/_threads/_team.py
twisted/_threads/_threadworker.py
twisted/_threads/test/__init__.py
twisted/_threads/test/test_convenience.py
twisted/_threads/test/test_memory.py
twisted/_threads/test/test_team.py
twisted/_threads/test/test_threadworker.py
twisted/application/__init__.py
twisted/application/app.py
twisted/application/internet.py
twisted/application/reactors.py
twisted/application/service.py
twisted/application/strports.py
twisted/application/runner/__init__.py
twisted/application/runner/_exit.py
twisted/application/runner/_pidfile.py
twisted/application/runner/_runner.py
twisted/application/runner/test/__init__.py
twisted/application/runner/test/test_exit.py
twisted/application/runner/test/test_pidfile.py
twisted/application/runner/test/test_runner.py
twisted/application/test/__init__.py
twisted/application/test/test_internet.py
twisted/application/test/test_service.py
twisted/application/twist/__init__.py
twisted/application/twist/_options.py
twisted/application/twist/_twist.py
twisted/application/twist/test/__init__.py
twisted/application/twist/test/test_options.py
twisted/application/twist/test/test_twist.py
twisted/conch/__init__.py
twisted/conch/avatar.py
twisted/conch/checkers.py
twisted/conch/endpoints.py
twisted/conch/error.py
twisted/conch/interfaces.py
twisted/conch/ls.py
twisted/conch/manhole.py
twisted/conch/manhole_ssh.py
twisted/conch/manhole_tap.py
twisted/conch/mixin.py
twisted/conch/recvline.py
twisted/conch/stdio.py
twisted/conch/tap.py
twisted/conch/telnet.py
twisted/conch/ttymodes.py
twisted/conch/unix.py
twisted/conch/client/__init__.py
twisted/conch/client/agent.py
twisted/conch/client/connect.py
twisted/conch/client/default.py
twisted/conch/client/direct.py
twisted/conch/client/knownhosts.py
Twisted_binary-20.3.0.dist-info/LICENSE
Twisted_binary-20.3.0.dist-info/METADATA
Twisted_binary-20.3.0.dist-info/WHEEL
Twisted_binary-20.3.0.dist-info/entry_points.txt
Twisted_binary-20.3.0.dist-info/top_level.txt
Twisted_binary-20.3.0.dist-info/RECORD
