Metadata-Version: 2.1
Name: Twisted-binary
Version: 20.3.0
Summary: (Non Official) Binary Build for Twisted-An asynchronous networking framework written in Python
Home-page: https://twistedmatrix.com/
Author: Lin Xiao Hui
Author-email: llinxiaohui@126.com
Maintainer: Lin Xiao Hui
Maintainer-email: llinxiaohui@126.com
License: MIT
Project-URL: Documentation, https://twistedmatrix.com/documents/current/
Project-URL: Source, https://github.com/twisted/twisted
Project-URL: Issues, https://twistedmatrix.com/trac/report
Platform: UNKNOWN
Classifier: Programming Language :: Python :: 3
Classifier: Programming Language :: Python :: 3.6
Classifier: Programming Language :: Python :: 3.8
Requires-Python: >=2.7,!=3.0.*,!=3.1.*,!=3.2.*,!=3.3.*,!=3.4.*
Requires-Dist: zope.interface (>=4.4.2)
Requires-Dist: constantly (>=15.1)
Requires-Dist: incremental (>=16.10.1)
Requires-Dist: Automat (>=0.3.0)
Requires-Dist: hyperlink (>=17.1.1)
Requires-Dist: PyHamcrest (!=1.10.0,>=1.9.0)
Requires-Dist: attrs (>=19.2.0)
Provides-Extra: all_non_platform
Requires-Dist: pyopenssl (>=16.0.0) ; extra == 'all_non_platform'
Requires-Dist: service-identity (>=18.1.0) ; extra == 'all_non_platform'
Requires-Dist: idna (!=2.3,>=0.6) ; extra == 'all_non_platform'
Requires-Dist: pyasn1 ; extra == 'all_non_platform'
Requires-Dist: cryptography (>=2.5) ; extra == 'all_non_platform'
Requires-Dist: appdirs (>=1.4.0) ; extra == 'all_non_platform'
Requires-Dist: bcrypt (>=3.0.0) ; extra == 'all_non_platform'
Requires-Dist: soappy ; extra == 'all_non_platform'
Requires-Dist: pyserial (>=3.0) ; extra == 'all_non_platform'
Requires-Dist: h2 (<4.0,>=3.0) ; extra == 'all_non_platform'
Requires-Dist: priority (<2.0,>=1.1.0) ; extra == 'all_non_platform'
Requires-Dist: pywin32 (!=226) ; (platform_system == "Windows") and extra == 'all_non_platform'
Provides-Extra: conch
Requires-Dist: pyasn1 ; extra == 'conch'
Requires-Dist: cryptography (>=2.5) ; extra == 'conch'
Requires-Dist: appdirs (>=1.4.0) ; extra == 'conch'
Requires-Dist: bcrypt (>=3.0.0) ; extra == 'conch'
Provides-Extra: dev
Requires-Dist: pyflakes (>=1.0.0) ; extra == 'dev'
Requires-Dist: twisted-dev-tools (>=0.0.2) ; extra == 'dev'
Requires-Dist: python-subunit ; extra == 'dev'
Requires-Dist: sphinx (>=1.3.1) ; extra == 'dev'
Requires-Dist: towncrier (>=17.4.0) ; extra == 'dev'
Provides-Extra: http2
Requires-Dist: h2 (<4.0,>=3.0) ; extra == 'http2'
Requires-Dist: priority (<2.0,>=1.1.0) ; extra == 'http2'
Provides-Extra: macos_platform
Requires-Dist: pyobjc-core ; extra == 'macos_platform'
Requires-Dist: pyobjc-framework-CFNetwork ; extra == 'macos_platform'
Requires-Dist: pyobjc-framework-Cocoa ; extra == 'macos_platform'
Requires-Dist: pyopenssl (>=16.0.0) ; extra == 'macos_platform'
Requires-Dist: service-identity (>=18.1.0) ; extra == 'macos_platform'
Requires-Dist: idna (!=2.3,>=0.6) ; extra == 'macos_platform'
Requires-Dist: pyasn1 ; extra == 'macos_platform'
Requires-Dist: cryptography (>=2.5) ; extra == 'macos_platform'
Requires-Dist: appdirs (>=1.4.0) ; extra == 'macos_platform'
Requires-Dist: bcrypt (>=3.0.0) ; extra == 'macos_platform'
Requires-Dist: soappy ; extra == 'macos_platform'
Requires-Dist: pyserial (>=3.0) ; extra == 'macos_platform'
Requires-Dist: h2 (<4.0,>=3.0) ; extra == 'macos_platform'
Requires-Dist: priority (<2.0,>=1.1.0) ; extra == 'macos_platform'
Requires-Dist: pywin32 (!=226) ; (platform_system == "Windows") and extra == 'macos_platform'
Provides-Extra: osx_platform
Requires-Dist: pyobjc-core ; extra == 'osx_platform'
Requires-Dist: pyobjc-framework-CFNetwork ; extra == 'osx_platform'
Requires-Dist: pyobjc-framework-Cocoa ; extra == 'osx_platform'
Requires-Dist: pyopenssl (>=16.0.0) ; extra == 'osx_platform'
Requires-Dist: service-identity (>=18.1.0) ; extra == 'osx_platform'
Requires-Dist: idna (!=2.3,>=0.6) ; extra == 'osx_platform'
Requires-Dist: pyasn1 ; extra == 'osx_platform'
Requires-Dist: cryptography (>=2.5) ; extra == 'osx_platform'
Requires-Dist: appdirs (>=1.4.0) ; extra == 'osx_platform'
Requires-Dist: bcrypt (>=3.0.0) ; extra == 'osx_platform'
Requires-Dist: soappy ; extra == 'osx_platform'
Requires-Dist: pyserial (>=3.0) ; extra == 'osx_platform'
Requires-Dist: h2 (<4.0,>=3.0) ; extra == 'osx_platform'
Requires-Dist: priority (<2.0,>=1.1.0) ; extra == 'osx_platform'
Requires-Dist: pywin32 (!=226) ; (platform_system == "Windows") and extra == 'osx_platform'
Provides-Extra: serial
Requires-Dist: pyserial (>=3.0) ; extra == 'serial'
Requires-Dist: pywin32 (!=226) ; (platform_system == "Windows") and extra == 'serial'
Provides-Extra: soap
Requires-Dist: soappy ; extra == 'soap'
Provides-Extra: tls
Requires-Dist: pyopenssl (>=16.0.0) ; extra == 'tls'
Requires-Dist: service-identity (>=18.1.0) ; extra == 'tls'
Requires-Dist: idna (!=2.3,>=0.6) ; extra == 'tls'
Provides-Extra: windows_platform
Requires-Dist: pywin32 (!=226) ; extra == 'windows_platform'
Requires-Dist: pyopenssl (>=16.0.0) ; extra == 'windows_platform'
Requires-Dist: service-identity (>=18.1.0) ; extra == 'windows_platform'
Requires-Dist: idna (!=2.3,>=0.6) ; extra == 'windows_platform'
Requires-Dist: pyasn1 ; extra == 'windows_platform'
Requires-Dist: cryptography (>=2.5) ; extra == 'windows_platform'
Requires-Dist: appdirs (>=1.4.0) ; extra == 'windows_platform'
Requires-Dist: bcrypt (>=3.0.0) ; extra == 'windows_platform'
Requires-Dist: soappy ; extra == 'windows_platform'
Requires-Dist: pyserial (>=3.0) ; extra == 'windows_platform'
Requires-Dist: h2 (<4.0,>=3.0) ; extra == 'windows_platform'
Requires-Dist: priority (<2.0,>=1.1.0) ; extra == 'windows_platform'
Requires-Dist: pywin32 (!=226) ; (platform_system == "Windows") and extra == 'windows_platform'
